broker/__init__.py
broker/base.py
broker/client.py
broker/exceptions.py
broker/websockets.py
examples/OkexWsLasttrade.py
examples/__init__.py
examples/contract-examples.py
examples/contract_limit_free.py
examples/contract_ws_example.py
examples/csv_t.py
examples/examples.py
examples/okex_gateway(1).py
examples/option-examples.py
examples/t.py
examples/ws_examples.py
examples/ws_test.py
examples/zlibt.py
broker_trade_client-2.1.1.dist-info/LICENSE
broker_trade_client-2.1.1.dist-info/METADATA
broker_trade_client-2.1.1.dist-info/WHEEL
broker_trade_client-2.1.1.dist-info/top_level.txt
broker_trade_client-2.1.1.dist-info/RECORD
